AUTHORS
HISTORY.rst
LICENSE
MANIFEST.in
README.rst
setup.py
tablib/__init__.py
tablib/compat.py
tablib/core.py
tablib/formats/__init__.py
tablib/formats/_csv.py
tablib/formats/_html.py
tablib/formats/_json.py
tablib/formats/_ods.py
tablib/formats/_tsv.py
tablib/formats/_xls.py
tablib/formats/_xlsx.py
tablib/formats/_yaml.py
tablib/packages/__init__.py
tablib/packages/markup.py
tablib/packages/markup3.py
tablib/packages/ordereddict.py
tablib/packages/odf/__init__.py
tablib/packages/odf/anim.py
tablib/packages/odf/attrconverters.py
tablib/packages/odf/chart.py
tablib/packages/odf/config.py
tablib/packages/odf/dc.py
tablib/packages/odf/dr3d.py
tablib/packages/odf/draw.py
tablib/packages/odf/easyliststyle.py
tablib/packages/odf/element.py
tablib/packages/odf/elementtypes.py
tablib/packages/odf/form.py
tablib/packages/odf/grammar.py
tablib/packages/odf/load.py
tablib/packages/odf/manifest.py
tablib/packages/odf/math.py
tablib/packages/odf/meta.py
tablib/packages/odf/namespaces.py
tablib/packages/odf/number.py
tablib/packages/odf/odf2moinmoin.py
tablib/packages/odf/odf2xhtml.py
tablib/packages/odf/odfmanifest.py
tablib/packages/odf/office.py
tablib/packages/odf/opendocument.py
tablib/packages/odf/presentation.py
tablib/packages/odf/script.py
tablib/packages/odf/style.py
tablib/packages/odf/svg.py
tablib/packages/odf/table.py
tablib/packages/odf/teletype.py
tablib/packages/odf/text.py
tablib/packages/odf/thumbnail.py
tablib/packages/odf/userfield.py
tablib/packages/odf/xforms.py
tablib/packages/odf3/__init__.py
tablib/packages/odf3/anim.py
tablib/packages/odf3/attrconverters.py
tablib/packages/odf3/chart.py
tablib/packages/odf3/config.py
tablib/packages/odf3/dc.py
tablib/packages/odf3/dr3d.py
tablib/packages/odf3/draw.py
tablib/packages/odf3/easyliststyle.py
tablib/packages/odf3/element.py
tablib/packages/odf3/elementtypes.py
tablib/packages/odf3/form.py
tablib/packages/odf3/grammar.py
tablib/packages/odf3/load.py
tablib/packages/odf3/manifest.py
tablib_garetjax.egg-info/PKG-INFO
tablib_garetjax.egg-info/SOURCES.txt
tablib_garetjax.egg-info/dependency_links.txt
tablib_garetjax.egg-info/top_level.txt